LICENSE.txt
MANIFEST.in
README
setup.cfg
setup.py
doc/Makefile
doc/source/api.rst
doc/source/calibration.rst
doc/source/calibration.rst~
doc/source/conf.py
doc/source/index.rst
doc/source/introduction.rst
mipp/__init__.py
mipp/cfg.py
mipp/log.py
mipp/mda.py
mipp/read_geotiff.py
mipp/version.py
mipp.egg-info/PKG-INFO
mipp.egg-info/SOURCES.txt
mipp.egg-info/dependency_links.txt
mipp.egg-info/not-zip-safe
mipp.egg-info/requires.txt
mipp.egg-info/top_level.txt
mipp/xrit/GOMS.py
mipp/xrit/H8.py
mipp/xrit/MSG.py
mipp/xrit/MTP.py
mipp/xrit/SGS.py
mipp/xrit/__init__.py
mipp/xrit/_xrit.py
mipp/xrit/bin_reader.py
mipp/xrit/convert.py
mipp/xrit/loader.py
mipp/xrit/mda.py
mipp/xrit/sat.py
mipp/xsar/CSK.py
mipp/xsar/RS2.py
mipp/xsar/S1A.py
mipp/xsar/TSX.py
mipp/xsar/__init__.py
mipp/xsar/mda.py
mipp/xsar/sat.py