Metadata-Version: 1.1
Name: mipp
Version: 1.1.0
Summary: Meteorological ingest processing package
Home-page: https://github.com/pytroll/mipp
Author: Lars Orum Rasmussen
Author-email: loerum@gmail.com
License: UNKNOWN
Download-URL: https://github.com/pytroll/mipp/releases/tag/v1.1.0
Platform: UNKNOWN
Classifier: Development Status :: 5 - Production/Stable
Classifier: Intended Audience :: Science/Research
Classifier: License :: OSI Approved :: GNU General Public License v3 or later (GPLv3+)
Classifier: Operating System :: OS Independent
Classifier: Programming Language :: Python
Classifier: Topic :: Scientific/Engineering
